voicecore/__init__.py
voicecore-0.1.0.dist-info/LICENSE
voicecore-0.1.0.dist-info/METADATA
voicecore-0.1.0.dist-info/WHEEL
voicecore-0.1.0.dist-info/top_level.txt
voicecore-0.1.0.dist-info/RECORD
