Metadata-Version: 2.1
Name: voicecore
Version: 0.1.0
Summary: The VoiceCore client library
Author-email: Dom <dom@voicecore.ai>
License: MIT License
Project-URL: Homepage, https://github.com/voicecore/voicecore
Requires-Python: >=3.6
License-File: LICENSE
Provides-Extra: dev
Requires-Dist: pytest; extra == "dev"
Requires-Dist: black; extra == "dev"
